q4/dataflow/sop_pos_function.vhd
library ieee;
use ieee.std_logic_1164.all;
use ieee.numeric_std.all;

entity sop_pos_function is
  port (
    x1, x2, x3, x4 : in std_logic;
    y_sop, y_pos : out std_logic
  );
end entity;

architecture dataflow of sop_pos_function is
  signal inputs : std_logic_vector(3 downto 0);
begin
  inputs <= x1 & x2 & x3 & x4;
  
  -- SOP Form : f = SUM(m0, m1, m4, m5, m8, m9, m14, m15)
  y_sop <= '1' when (inputs = "0000") or -- m0
            (inputs = "0001") or --m1
            (inputs = "0100") or --m4
            (inputs = "0101") or --m5
            (inputs = "1000") or --m8
            (inputs = "1001") or --m9
            (inputs = "1110") or --m14
            (inputs = "1111") else '0'; --m15

  y_pos <= '0' when (inputs = "0000") or --m0
           (inputs = "0001") or --m1
           (inputs = "0101") or --m5
           (inputs = "1000") or --m8
           (inputs = "1001") or --m9
           (inputs = "1101") or --m13
           (inputs = "1111") else '1'; --m15

end architecture;

q4/dataflow/sop_pos_function_tb.vhd
library ieee;
use ieee.std_logic_1164.all;
use ieee.numeric_std.all;

entity sop_pos_function_tb is
end entity;

architecture sim of sop_pos_function_tb is
  signal x1, x2, x3, x4 : std_logic := '0';
  signal y_sop, y_pos : std_logic;
  signal test_vector : std_logic_vector(3 downto 0);

begin
  UUT: entity work.sop_pos_function(dataflow)
    port map(
      x1 => x1, x2 => x2, x3 => x3, x4 => x4,
      y_sop => y_sop, y_pos => y_pos
    );

    -- connect test vector to inputs
    x1 <= test_vector(3);
    x2 <= test_vector(2);
    x3 <= test_vector(1);
    x4 <= test_vector(0);

    -- test process
    process
    begin
      for i in 0 to 15 loop
        test_vector <= std_logic_vector(to_unsigned(i, 4));
        wait for 10 ns;
      end loop;

      report "Simulation complete";
      wait;
    end process;

end architecture;

q4/dataflow/waveform.vcd
$date
  Thu Feb 26 12:02:54 2026
$end
$version
  GHDL v0
$end
$timescale
  1 fs
$end
$scope module standard $end
$upscope $end
$scope module std_logic_1164 $end
$upscope $end
$scope module numeric_std $end
$upscope $end
$scope module sop_pos_function_tb $end
$var reg 1 ! x1 $end
$var reg 1 " x2 $end
$var reg 1 # x3 $end
$var reg 1 $ x4 $end
$var reg 1 % y_sop $end
$var reg 1 & y_pos $end
$var reg 4 ' test_vector[3:0] $end
$scope module uut $end
$var reg 1 ( x1 $end
$var reg 1 ) x2 $end
$var reg 1 * x3 $end
$var reg 1 + x4 $end
$var reg 1 , y_sop $end
$var reg 1 - y_pos $end
$var reg 4 . inputs[3:0] $end
$upscope $end
$upscope $end
$enddefinitions $end
#0
0!
0"
0#
0$
1%
0&
b0000 '
0(
0)
0*
0+
1,
0-
b0000 .
#10000000
1$
b0001 '
1+
b0001 .
#20000000
1#
0$
0%
1&
b0010 '
1*
0+
0,
1-
b0010 .
#30000000
1$
b0011 '
1+
b0011 .
#40000000
1"
0#
0$
1%
b0100 '
1)
0*
0+
1,
b0100 .
#50000000
1$
0&
b0101 '
1+
0-
b0101 .
#60000000
1#
0$
0%
1&
b0110 '
1*
0+
0,
1-
b0110 .
#70000000
1$
b0111 '
1+
b0111 .
#80000000
1!
0"
0#
0$
1%
0&
b1000 '
1(
0)
0*
0+
1,
0-
b1000 .
#90000000
1$
b1001 '
1+
b1001 .
#100000000
1#
0$
0%
1&
b1010 '
1*
0+
0,
1-
b1010 .
#110000000
1$
b1011 '
1+
b1011 .
#120000000
1"
0#
0$
b1100 '
1)
0*
0+
b1100 .
#130000000
1$
0&
b1101 '
1+
0-
b1101 .
#140000000
1#
0$
1%
1&
b1110 '
1*
0+
1,
1-
b1110 .
#150000000
1$
0&
b1111 '
1+
0-
b1111 .
