q7/full_adder.vhd
library ieee;
use ieee.std_logic_1164.all;

entity full_adder is
  port (
    a, b, cin : in std_logic;
    sum, cout : out std_logic
  );
end entity;

architecture behavioral of full_adder is
begin
  process(a, b, cin)
  begin
    sum <= a xor b xor cin;
    cout <= (a and b) or (a and cin) or (b and cin);
  end process;
end architecture;

q7/alu.vhd
library ieee;
use ieee.std_logic_1164.all;
use ieee.numeric_std.all;

entity alu is
    port (
        a     : in  std_logic_vector(3 downto 0);
        b     : in  std_logic_vector(3 downto 0);
        mode  : in  std_logic;
        sum   : out std_logic_vector(3 downto 0);
        carry : out std_logic
    );
end entity alu;

architecture structural of alu is
    component full_adder is
        port (
            a    : in  std_logic;
            b    : in  std_logic;
            cin  : in  std_logic;
            sum  : out std_logic;
            cout : out std_logic
        );
    end component;

    -- Internal signals
    signal b_xor     : std_logic_vector(3 downto 0);
    signal carry_int : std_logic_vector(3 downto 0);

begin
    b_xor <= b xor (mode & mode & mode & mode);

    fa0: full_adder port map (
        a    => a(0),
        b    => b_xor(0),
        cin  => mode,
        sum  => sum(0),
        cout => carry_int(0)
    );

    fa1: full_adder port map (
        a    => a(1),
        b    => b_xor(1),
        cin  => carry_int(0),
        sum  => sum(1),
        cout => carry_int(1)
    );

    fa2: full_adder port map (
        a    => a(2),
        b    => b_xor(2),
        cin  => carry_int(1),
        sum  => sum(2),
        cout => carry_int(2)
    );

    fa3: full_adder port map (
        a    => a(3),
        b    => b_xor(3),
        cin  => carry_int(2),
        sum  => sum(3),
        cout => carry_int(3)
    );

    carry <= carry_int(3);

end architecture structural;

q7/alu_tb.vhd
library ieee;
use ieee.std_logic_1164.all;
use ieee.numeric_std.all;

entity alu_tb is
end entity alu_tb;

architecture behavioral of alu_tb is
    component alu is
        port (
            a     : in  std_logic_vector(3 downto 0);
            b     : in  std_logic_vector(3 downto 0);
            mode  : in  std_logic;
            sum   : out std_logic_vector(3 downto 0);
            carry : out std_logic
        );
    end component;

    -- Test signals
    signal a_tb     : std_logic_vector(3 downto 0) := (others => '0');
    signal b_tb     : std_logic_vector(3 downto 0) := (others => '0');
    signal mode_tb  : std_logic := '0';
    signal sum_tb   : std_logic_vector(3 downto 0);
    signal carry_tb : std_logic;

begin
    uut: alu port map (
        a     => a_tb,
        b     => b_tb,
        mode  => mode_tb,
        sum   => sum_tb,
        carry => carry_tb
    );

    -- test process
    process
    begin
        -- test Addition (mode = '0')
        report "Testing Addition Mode (mode = '0'):";
        mode_tb <= '0';
        
        -- test case 1: 5 + 3 = 8 (with carry 0)
        a_tb <= "0101";  -- 5
        b_tb <= "0011";  -- 3
        wait for 10 ns;
        
        -- test case 2: 9 + 6 = 15 (with carry 0)
        a_tb <= "1001";  -- 9
        b_tb <= "0110";  -- 6
        wait for 10 ns;
        
        -- test case 3: 12 + 5 = 17 (with carry 1)
        a_tb <= "1100";  -- 12
        b_tb <= "0101";  -- 5
        wait for 10 ns;
        
        -- test case 4: 15 + 1 = 16 (with carry 1)
        a_tb <= "1111";  -- 15
        b_tb <= "0001";  -- 1
        wait for 10 ns;
        
        -- test Subtraction (mode = '1')
        report "Testing Subtraction Mode (mode = '1'):";
        mode_tb <= '1';
        
        -- test case 5: 8 - 3 = 5 (with borrow 0)
        a_tb <= "1000";  -- 8
        b_tb <= "0011";  -- 3
        wait for 10 ns;
        
        -- test case 6: 15 - 7 = 8 (with borrow 0)
        a_tb <= "1111";  -- 15
        b_tb <= "0111";  -- 7
        wait for 10 ns;
        
        -- test case 7: 5 - 8 = -3 (2's complement: 13 with borrow 1)
        a_tb <= "0101";  -- 5
        b_tb <= "1000";  -- 8
        wait for 10 ns;
        
        -- test case 8: 12 - 15 = -3 (2's complement: 13 with borrow 1)
        a_tb <= "1100";  -- 12
        b_tb <= "1111";  -- 15
        wait for 10 ns;
        
        -- test boundary conditions
        report "Testing Boundary Conditions:";
        
        -- tst case 9: 0 + 0 = 0
        mode_tb <= '0';
        a_tb <= "0000";
        b_tb <= "0000";
        wait for 10 ns;
        
        -- test case 10: 15 - 15 = 0
        mode_tb <= '1';
        a_tb <= "1111";
        b_tb <= "1111";
        wait for 10 ns;
        
        -- test case 11: 15 - 0 = 15
        mode_tb <= '1';
        a_tb <= "1111";
        b_tb <= "0000";
        wait for 10 ns;
        
        -- test case 12: 0 - 1 = -1 (15 with borrow 1)
        mode_tb <= '1';
        a_tb <= "0000";
        b_tb <= "0001";
        wait for 10 ns;
        
        report "Simulation completed successfully!";
        wait;
    end process;

end architecture behavioral;

q7/waveform.vcd
$date
  Thu Feb 26 20:30:15 2026
$end
$version
  GHDL v0
$end
$timescale
  1 fs
$end
$scope module standard $end
$upscope $end
$scope module std_logic_1164 $end
$upscope $end
$scope module numeric_std $end
$upscope $end
$scope module alu_tb $end
$var reg 4 ! a_tb[3:0] $end
$var reg 4 " b_tb[3:0] $end
$var reg 1 # mode_tb $end
$var reg 4 $ sum_tb[3:0] $end
$var reg 1 % carry_tb $end
$scope module uut $end
$var reg 4 & a[3:0] $end
$var reg 4 ' b[3:0] $end
$var reg 1 ( mode $end
$var reg 4 ) sum[3:0] $end
$var reg 1 * carry $end
$var reg 4 + b_xor[3:0] $end
$var reg 4 , carry_int[3:0] $end
$scope module fa0 $end
$var reg 1 - a $end
$var reg 1 . b $end
$var reg 1 / cin $end
$var reg 1 0 sum $end
$var reg 1 1 cout $end
$upscope $end
$scope module fa1 $end
$var reg 1 2 a $end
$var reg 1 3 b $end
$var reg 1 4 cin $end
$var reg 1 5 sum $end
$var reg 1 6 cout $end
$upscope $end
$scope module fa2 $end
$var reg 1 7 a $end
$var reg 1 8 b $end
$var reg 1 9 cin $end
$var reg 1 : sum $end
$var reg 1 ; cout $end
$upscope $end
$scope module fa3 $end
$var reg 1 < a $end
$var reg 1 = b $end
$var reg 1 > cin $end
$var reg 1 ? sum $end
$var reg 1 @ cout $end
$upscope $end
$upscope $end
$upscope $end
$enddefinitions $end
#0
b0101 !
b0011 "
0#
b1000 $
0%
b0101 &
b0011 '
0(
b1000 )
0*
b0011 +
b0111 ,
1-
1.
0/
00
11
02
13
14
05
16
17
08
19
0:
1;
0<
0=
1>
1?
0@
#10000000
b1001 !
b0110 "
b1111 $
0%
b1001 &
b0110 '
b1111 )
0*
b0110 +
b0000 ,
0.
10
01
04
15
06
07
18
09
1:
0;
1<
0>
1?
0@
#20000000
b1100 !
b0101 "
b0001 $
1%
b1100 &
b0101 '
b0001 )
1*
b0101 +
b1100 ,
0-
1.
10
03
05
17
0:
1;
1>
0?
1@
#30000000
b1111 !
b0001 "
b0000 $
1%
b1111 &
b0001 '
b0000 )
1*
b0001 +
b1111 ,
1-
00
11
12
14
05
16
08
19
0:
1;
1>
0?
1@
#40000000
b1000 !
b0011 "
1#
b0101 $
b1000 &
b0011 '
1(
b0101 )
b1100 +
b1000 ,
0-
0.
1/
10
01
02
04
05
06
07
18
09
1:
0;
1=
0>
#50000000
b1111 !
b0111 "
b1000 $
b1111 &
b0111 '
b1000 )
b1000 +
b1111 ,
1-
00
11
12
14
05
16
17
08
19
0:
1;
1>
1?
#60000000
b0101 !
b1000 "
b1101 $
0%
b0101 &
b1000 '
b1101 )
0*
b0111 +
b0111 ,
1.
10
02
13
05
16
18
19
1:
0<
0=
1?
0@
#70000000
b1100 !
b1111 "
b1101 $
0%
b1100 &
b1111 '
b1101 )
0*
b0000 +
b0000 ,
0-
0.
10
01
03
04
05
06
08
09
1:
0;
1<
0>
1?
0@
#80000000
b0000 !
b0000 "
0#
b0000 $
b0000 &
b0000 '
0(
b0000 )
0/
00
07
0:
0<
0?
#90000000
b1111 !
b1111 "
1#
b0000 $
1%
b1111 &
b1111 '
1(
b0000 )
1*
b1111 ,
1-
1/
11
12
14
05
16
17
19
0:
1;
1<
1>
0?
1@
#100000000
b0000 "
b1111 $
b0000 '
b1111 )
b1111 +
1.
10
13
15
18
1:
1=
1?
#110000000
b0000 !
b0001 "
b1111 $
0%
b0000 &
b0001 '
b1111 )
0*
b1110 +
b0000 ,
0-
0.
10
01
02
04
15
06
07
09
1:
0;
0<
0>
1?
0@
