q1/structural/or_gate.vhd
library ieee;
use ieee.std_logic_1164.all;

entity or_gate is
    port (
        a, b : in  std_logic;
        y    : out std_logic
    );
end entity;

architecture behavioral of or_gate is
begin
    y <= a or b;
end architecture;

q1/structural/and3_gate.vhd
library ieee;
use ieee.std_logic_1164.all;

entity and3_gate is
    port (
        a, b, c : in  std_logic;
        y       : out std_logic
    );
end entity;

architecture behavioral of and3_gate is
begin
    y <= a and b and c;
end architecture;

q1/structural/and_gate.vhd
library ieee;
use ieee.std_logic_1164.all;

entity and_gate is
    port (
        a, b : in  std_logic;
        y    : out std_logic
    );
end entity;

architecture behavioral of and_gate is
begin
    y <= a and b;
end architecture;

q1/structural/not_gate.vhd
library ieee;
use ieee.std_logic_1164.all;

entity not_gate is
    port (
        a : in  std_logic;
        y : out std_logic
    );
end entity;

architecture behavioral of not_gate is
begin
    y <= not a;
end architecture;

q1/structural/logic_circuit.vhd
library ieee;
use ieee.std_logic_1164.all;

entity logic_circuit is
  port (
    x1, x2, x3, x4  : in std_logic;
    f               : out std_logic
  );
end entity;

architecture structural of logic_circuit is
  -- component declarations
  component and_gate is
    port (
      a, b : in std_logic;
      y    : out std_logic
    );
  end component;

  component or_gate is
    port (
      a, b : in std_logic;
      y    : out std_logic
    );
  end component;

  component not_gate is
    port (
      a : in std_logic;
      y : out std_logic
    );
  end component;

  component and3_gate is
    port (
      a, b, c : in std_logic;
      y       : out std_logic
    );
  end component;

  -- internal signals
  signal BC, A_B, BC_C, A_C, BC_D : std_logic;
begin
  U1: not_gate port map (a => x2, y => BC);

  U2: and_gate port map (a => x1, b => x2, y => A_B);

  U3: and_gate port map (a => BC, b => x3, y => BC_C);

  U4: or_gate port map (a => A_B, b => BC_C, y => A_C);

  U5: and3_gate port map (a => BC, b => x3, c => x4, y => BC_D);

  U6: or_gate port map (a => A_C, b => BC_D, y => f);

end architecture;

q1/structural/q1_tb.vhd
library ieee;
use ieee.std_logic_1164.all;

entity q1_tb is
end entity;

architecture sim of q1_tb is
  signal x1, x2, x3, x4 : std_logic := '0';
  signal f : std_logic;
  
  -- array type for test vectors
  type test_vector is array (0 to 15) of std_logic_vector(3 downto 0);
  constant test_vectors : test_vector := (
    "0000", "0001", "0010", "0011",
    "0100", "0101", "0110", "0111",
    "1000", "1001", "1010", "1011",
    "1100", "1101", "1110", "1111"
  );
  
begin
  -- unit under test - using structural architecture
  UUT: entity work.logic_circuit(structural)
    port map(x1 => x1, x2 => x2, x3 => x3, x4 => x4, f => f);

  process
  begin
    -- iterate through all test vectors
    for i in 0 to 15 loop
      (x4, x3, x2, x1) <= test_vectors(i);
      wait for 10 ns;
    end loop;
    
    -- stop simulation
    wait;
  end process;
end architecture;

q1/structural/waveform.vcd
$date
  Wed Feb 25 23:32:54 2026
$end
$version
  GHDL v0
$end
$timescale
  1 fs
$end
$scope module standard $end
$upscope $end
$scope module std_logic_1164 $end
$upscope $end
$scope module q1_tb $end
$var reg 1 ! x1 $end
$var reg 1 " x2 $end
$var reg 1 # x3 $end
$var reg 1 $ x4 $end
$var reg 1 % f $end
$scope module uut $end
$var reg 1 & x1 $end
$var reg 1 ' x2 $end
$var reg 1 ( x3 $end
$var reg 1 ) x4 $end
$var reg 1 * f $end
$var reg 1 + bc $end
$var reg 1 , a_b $end
$var reg 1 - bc_c $end
$var reg 1 . a_c $end
$var reg 1 / bc_d $end
$scope module u1 $end
$var reg 1 0 a $end
$var reg 1 1 y $end
$upscope $end
$scope module u2 $end
$var reg 1 2 a $end
$var reg 1 3 b $end
$var reg 1 4 y $end
$upscope $end
$scope module u3 $end
$var reg 1 5 a $end
$var reg 1 6 b $end
$var reg 1 7 y $end
$upscope $end
$scope module u4 $end
$var reg 1 8 a $end
$var reg 1 9 b $end
$var reg 1 : y $end
$upscope $end
$scope module u5 $end
$var reg 1 ; a $end
$var reg 1 < b $end
$var reg 1 = c $end
$var reg 1 > y $end
$upscope $end
$scope module u6 $end
$var reg 1 ? a $end
$var reg 1 @ b $end
$var reg 1 A y $end
$upscope $end
$upscope $end
$upscope $end
$enddefinitions $end
#0
0!
0"
0#
0$
0%
0&
0'
0(
0)
0*
1+
0,
0-
0.
0/
00
11
02
03
04
15
06
07
08
09
0:
1;
0<
0=
0>
0?
0@
0A
#10000000
1!
1&
12
#20000000
0!
1"
0&
1'
0+
10
01
02
13
05
0;
#30000000
1!
1%
1&
1*
1,
1.
12
14
18
1:
1?
1A
#40000000
0!
0"
1#
1%
0&
0'
1(
1*
1+
0,
1-
1.
00
11
02
03
04
15
16
17
08
19
1:
1;
1<
1?
1A
#50000000
1!
1&
12
#60000000
0!
1"
0%
0&
1'
0*
0+
0-
0.
10
01
02
13
05
07
09
0:
0;
0?
0A
#70000000
1!
1%
1&
1*
1,
1.
12
14
18
1:
1?
1A
#80000000
0!
0"
0#
1$
0%
0&
0'
0(
1)
0*
1+
0,
0.
00
11
02
03
04
15
06
08
0:
1;
0<
1=
0?
0A
#90000000
1!
1&
12
#100000000
0!
1"
0&
1'
0+
10
01
02
13
05
0;
#110000000
1!
1%
1&
1*
1,
1.
12
14
18
1:
1?
1A
#120000000
0!
0"
1#
0&
0'
1(
1+
0,
1-
1.
1/
00
11
02
03
04
15
16
17
08
19
1:
1;
1<
1>
1?
1@
#130000000
1!
1&
12
#140000000
0!
1"
0%
0&
1'
0*
0+
0-
0.
0/
10
01
02
13
05
07
09
0:
0;
0>
0?
0@
0A
#150000000
1!
1%
1&
1*
1,
1.
12
14
18
1:
1?
1A
