q3/structural/nor_gate.vhd
library ieee;
use ieee.std_logic_1164.all;

entity nor_gate is
  port (
    a, b : in std_logic;
    y : out std_logic
  );
end entity;

architecture behavioral of nor_gate is
begin
  y <= not (a or b);
end architecture;

q3/structural/majority_2_of_3.vhd
library ieee;
use ieee.std_logic_1164.all;

entity majority_2_of_3 is
  port (
    x1, x2, x3 : in std_logic;
    y : out std_logic
  );
end entity;

architecture structural_nor of majority_2_of_3 is
  -- nor gate component
  component nor_gate is
    port (
      a, b : in std_logic;
      y : out std_logic
    );
  end component;
  
  -- internal signals
  signal n_x2_x3, n_x2_n_x2x3, n_x3_n_x2x3, xor_x2_x3 : std_logic;

  -- for NOT x1
  signal not_x1 : std_logic;

  -- for AND of x1 and xor_x2_x3
  signal n_x1, n_xor, and1 : std_logic;

  -- for AND of not_x1, x2, x3
  signal n_not_x1, n_x2_for_and2, n_x3_for_and2, and2_temp, and2 : std_logic;
  signal n_and2_temp : std_logic;

  -- for OR of and1 and and2
  signal n_or_inputs, or_final : std_logic;

begin
  -- generate NOT x1
  not1: nor_gate port map (a => x1, b => x1, y => not_x1);

  -- generate XOR of x2 and x3
  nor_xor1: nor_gate port map(a => x2, b => x3, y => n_x2_x3);
  nor_xor2: nor_gate port map(a => x2, b => n_x2_x3, y => n_x2_n_x2x3);
  nor_xor3: nor_gate port map(a => x3, b => n_x2_x3, y => n_x3_n_x2x3);
  nor_xor4: nor_gate port map(a => n_x2_n_x2x3, b => n_x3_n_x2x3, y => xor_x2_x3);

  -- generate AND of x1 and xor_x2_x3
  nor_and1_1: nor_gate port map (a => x1, b => x1, y => n_x1);
  nor_and1_2: nor_gate port map (a => xor_x2_x3, b => xor_x2_x3, y => n_xor);
  nor_and1_3: nor_gate port map (a => n_x1, b => n_xor, y => and1);

  -- generate AND of not_x1, x2, x3
  nor_and2_1: nor_gate port map (a => not_x1, b => not_x1, y => n_not_x1);
  nor_and2_2: nor_gate port map (a => x2, b => x2, y => n_x2_for_and2);
  nor_and2_3: nor_gate port map (a => n_not_x1, b => n_x2_for_and2, y => and2_temp);
  
  -- then AND the result with x3
  nor_and2_4: nor_gate port map (a => and2_temp, b => and2_temp, y => n_and2_temp);
  nor_and2_5: nor_gate port map (a => x3, b => x3, y => n_x3_for_and2);
  nor_and2_6: nor_gate port map (a => n_and2_temp, b => n_x3_for_and2, y => and2);

  -- generate OR of and1 and and2
  nor_or1: nor_gate port map (a => and1, b => and2, y => n_or_inputs);
  nor_or2: nor_gate port map (a => n_or_inputs, b => n_or_inputs, y => or_final);
  
  y <= or_final;

end architecture;

q3/structural/majority_2_of_3_tb.vhd
library ieee;
use ieee.std_logic_1164.all;
use ieee.numeric_std.all;

entity majority_2_of_3_tb is
end entity;

architecture sim of majority_2_of_3_tb is
  signal x1, x2, x3 : std_logic := '0';
  signal y : std_logic;
  signal test_vector : std_logic_vector(2 downto 0);

begin
  -- uut for dataflow
  UUT: entity work.majority_2_of_3(structural_nor)
    port map(
      x1 => x1, x2 => x2, x3 => x3, y => y
    );

  x1 <= test_vector(2);
  x2 <= test_vector(1);
  x3 <= test_vector(0);

  process
  begin
    for i in 0 to 7 loop
      test_vector <= std_logic_vector(to_unsigned(i, 3));
      wait for 10 ns;
    end loop;
    wait;
  end process;
end architecture;

q3/structural/waveform.vcd
$date
  Thu Feb 26 11:30:55 2026
$end
$version
  GHDL v0
$end
$timescale
  1 fs
$end
$scope module standard $end
$upscope $end
$scope module std_logic_1164 $end
$upscope $end
$scope module numeric_std $end
$upscope $end
$scope module majority_2_of_3_tb $end
$var reg 1 ! x1 $end
$var reg 1 " x2 $end
$var reg 1 # x3 $end
$var reg 1 $ y $end
$var reg 3 % test_vector[2:0] $end
$scope module uut $end
$var reg 1 & x1 $end
$var reg 1 ' x2 $end
$var reg 1 ( x3 $end
$var reg 1 ) y $end
$var reg 1 * n_x2_x3 $end
$var reg 1 + n_x2_n_x2x3 $end
$var reg 1 , n_x3_n_x2x3 $end
$var reg 1 - xor_x2_x3 $end
$var reg 1 . not_x1 $end
$var reg 1 / n_x1 $end
$var reg 1 0 n_xor $end
$var reg 1 1 and1 $end
$var reg 1 2 n_not_x1 $end
$var reg 1 3 n_x2_for_and2 $end
$var reg 1 4 n_x3_for_and2 $end
$var reg 1 5 and2_temp $end
$var reg 1 6 and2 $end
$var reg 1 7 n_and2_temp $end
$var reg 1 8 n_or_inputs $end
$var reg 1 9 or_final $end
$scope module not1 $end
$var reg 1 : a $end
$var reg 1 ; b $end
$var reg 1 < y $end
$upscope $end
$scope module nor_xor1 $end
$var reg 1 = a $end
$var reg 1 > b $end
$var reg 1 ? y $end
$upscope $end
$scope module nor_xor2 $end
$var reg 1 @ a $end
$var reg 1 A b $end
$var reg 1 B y $end
$upscope $end
$scope module nor_xor3 $end
$var reg 1 C a $end
$var reg 1 D b $end
$var reg 1 E y $end
$upscope $end
$scope module nor_xor4 $end
$var reg 1 F a $end
$var reg 1 G b $end
$var reg 1 H y $end
$upscope $end
$scope module nor_and1_1 $end
$var reg 1 I a $end
$var reg 1 J b $end
$var reg 1 K y $end
$upscope $end
$scope module nor_and1_2 $end
$var reg 1 L a $end
$var reg 1 M b $end
$var reg 1 N y $end
$upscope $end
$scope module nor_and1_3 $end
$var reg 1 O a $end
$var reg 1 P b $end
$var reg 1 Q y $end
$upscope $end
$scope module nor_and2_1 $end
$var reg 1 R a $end
$var reg 1 S b $end
$var reg 1 T y $end
$upscope $end
$scope module nor_and2_2 $end
$var reg 1 U a $end
$var reg 1 V b $end
$var reg 1 W y $end
$upscope $end
$scope module nor_and2_3 $end
$var reg 1 X a $end
$var reg 1 Y b $end
$var reg 1 Z y $end
$upscope $end
$scope module nor_and2_4 $end
$var reg 1 [ a $end
$var reg 1 \ b $end
$var reg 1 ] y $end
$upscope $end
$scope module nor_and2_5 $end
$var reg 1 ^ a $end
$var reg 1 _ b $end
$var reg 1 ` y $end
$upscope $end
$scope module nor_and2_6 $end
$var reg 1 a a $end
$var reg 1 b b $end
$var reg 1 c y $end
$upscope $end
$scope module nor_or1 $end
$var reg 1 d a $end
$var reg 1 e b $end
$var reg 1 f y $end
$upscope $end
$scope module nor_or2 $end
$var reg 1 g a $end
$var reg 1 h b $end
$var reg 1 i y $end
$upscope $end
$upscope $end
$upscope $end
$enddefinitions $end
#0
0!
0"
0#
0$
b000 %
0&
0'
0(
0)
1*
0+
0,
1-
1.
1/
00
01
02
13
14
05
06
17
18
09
0:
0;
1<
0=
0>
1?
0@
1A
0B
0C
1D
0E
0F
0G
1H
0I
0J
1K
1L
1M
0N
1O
0P
0Q
1R
1S
0T
0U
0V
1W
0X
1Y
0Z
0[
0\
1]
0^
0_
1`
1a
1b
0c
0d
0e
1f
1g
1h
0i
#10000000
1#
b001 %
1(
0*
1+
0-
10
04
1>
0?
0A
1B
1C
0D
1F
0H
0L
0M
1N
1P
1^
1_
0`
0b
#20000000
1"
0#
b010 %
1'
0(
0+
1,
03
14
15
07
1=
0>
1@
0B
0C
1E
0F
1G
1U
1V
0W
0Y
1Z
1[
1\
0]
0^
0_
1`
0a
1b
#30000000
1#
1$
b011 %
1(
1)
0,
1-
00
04
16
08
19
1>
1C
0E
0G
1H
1L
1M
0N
0P
1^
1_
0`
0b
1c
1e
0f
0g
0h
1i
#40000000
1!
0"
0#
1$
b100 %
1&
0'
0(
1)
1*
0+
0,
1-
0.
0/
00
11
12
13
14
05
06
17
08
19
1:
1;
0<
0=
0>
1?
0@
1A
0B
0C
1D
0E
0F
0G
1H
1I
1J
0K
1L
1M
0N
0O
0P
1Q
0R
0S
1T
0U
0V
1W
1X
1Y
0Z
0[
0\
1]
0^
0_
1`
1a
1b
0c
1d
0e
0f
0g
0h
1i
#50000000
1#
0$
b101 %
1(
0)
0*
1+
0-
10
01
04
18
09
1>
0?
0A
1B
1C
0D
1F
0H
0L
0M
1N
1P
0Q
1^
1_
0`
0b
0d
1f
1g
1h
0i
#60000000
1"
0#
b110 %
1'
0(
0+
1,
03
14
1=
0>
1@
0B
0C
1E
0F
1G
1U
1V
0W
0Y
0^
0_
1`
1b
#70000000
1#
1$
b111 %
1(
1)
0,
1-
00
11
04
08
19
1>
1C
0E
0G
1H
1L
1M
0N
0P
1Q
1^
1_
0`
0b
1d
0f
0g
0h
1i
