q3/behavioral/majority_2_of_3.vhd
library ieee;
use ieee.std_logic_1164.all;
use ieee.numeric_std.all;

entity majority_2_of_3 is
  port (
    x1, x2, x3 : in std_logic;
    y : out std_logic
  );
end entity;

architecture behavioral of majority_2_of_3 is
begin
   process(x1, x2, x3)
     variable inputs : std_logic_vector(2 downto 0);
     variable count: integer;
  begin
    inputs := x1 & x2 & x3;
    count := 0;

    if x1 = '1' then count := count + 1; end if;
    if x2 = '1' then count := count + 1; end if;
    if x3 = '1' then count := count + 1; end if;

    if count = 2 then
      y <= '1';
    else
      y <= '0';
    end if;
  end process;
end architecture;

q3/behavioral/majority_2_of_3_tb.vhd
library ieee;
use ieee.std_logic_1164.all;
use ieee.numeric_std.all;

entity majority_2_of_3_tb is
end entity;

architecture sim of majority_2_of_3_tb is
  signal x1, x2, x3 : std_logic := '0';
  signal y : std_logic;
  signal test_vector : std_logic_vector(2 downto 0);

begin
  -- uut for dataflow
  UUT: entity work.majority_2_of_3(behavioral)
    port map(
      x1 => x1, x2 => x2, x3 => x3, y => y
    );

  x1 <= test_vector(2);
  x2 <= test_vector(1);
  x3 <= test_vector(0);

  process
  begin
    for i in 0 to 7 loop
      test_vector <= std_logic_vector(to_unsigned(i, 3));
      wait for 10 ns;
    end loop;
    wait;
  end process;
end architecture;

q3/behavioral/waveform.vcd
$date
  Thu Feb 26 11:10:28 2026
$end
$version
  GHDL v0
$end
$timescale
  1 fs
$end
$scope module standard $end
$upscope $end
$scope module std_logic_1164 $end
$upscope $end
$scope module numeric_std $end
$upscope $end
$scope module majority_2_of_3_tb $end
$var reg 1 ! x1 $end
$var reg 1 " x2 $end
$var reg 1 # x3 $end
$var reg 1 $ y $end
$var reg 3 % test_vector[2:0] $end
$scope module uut $end
$var reg 1 & x1 $end
$var reg 1 ' x2 $end
$var reg 1 ( x3 $end
$var reg 1 ) y $end
$upscope $end
$upscope $end
$enddefinitions $end
#0
0!
0"
0#
0$
b000 %
0&
0'
0(
0)
#10000000
1#
b001 %
1(
#20000000
1"
0#
b010 %
1'
0(
#30000000
1#
1$
b011 %
1(
1)
#40000000
1!
0"
0#
0$
b100 %
1&
0'
0(
0)
#50000000
1#
1$
b101 %
1(
1)
#60000000
1"
0#
b110 %
1'
0(
#70000000
1#
0$
b111 %
1(
0)
