q3/structural/nor_gate.vhd
library ieee;
use ieee.std_logic_1164.all;

entity nor_gate is
  port (
    a, b : in std_logic;
    y : out std_logic
  );
end entity;

architecture behavioral of nor_gate is
begin
  y <= not (a or b);
end architecture;

q4/structural/sop_pos_function.vhd
library ieee;
use ieee.std_logic_1164.all;

entity sop_pos_function is
  port (
    x1, x2, x3, x4 : in std_logic;
    y_sop, y_pos : out std_logic
  );
end entity;

architecture structural_nor of sop_pos_function is
  component nor_gate is
    port (a, b : in std_logic; y : out std_logic);
  end component;

  signal A_not, B_not, C_not, D_not : std_logic;
  signal AB, AC_BC_CC, ABComp, ABC, y_sop_c : std_logic;
  signal C_DC, B_C, ABD, CDBC, CDBC_C : std_logic;

begin
  not_A: nor_gate port map (a => x1, b => x1, y => A_not);
  not_B: nor_gate port map (a => x2, b => x2, y => B_not);
  not_C: nor_gate port map (a => x3, b => x3, y => C_not);
  not_D: nor_gate port map (a => x4, b => x4, y => D_not);
  
  nor_1: nor_gate port map (a => A_not, b => B_not, y => AB);
  nor_2: nor_gate port map (a => AB, b => C_not, y => AC_BC_CC);
  nor_3: nor_gate port map (a => AB, b => AB, y => ABComp);
  nor_4: nor_gate port map (a => ABComp, b => C_not, y => ABC);
  nor_5: nor_gate port map (a => AC_BC_CC, b => ABC, y => y_sop_c);
  nor_6: nor_gate port map (a => y_sop_c, b => y_sop_c, y => y_sop);

  nor_7: nor_gate port map (a => x3, b => D_not, y => C_DC);
  nor_8: nor_gate port map (a => x2, b => x3, y => B_C);
  nor_9: nor_gate port map (a => ABComp, b => D_not, y => ABD);
  nor_10: nor_gate port map (a => C_DC, b => B_C, y => CDBC);
  nor_11: nor_gate port map (a => CDBC, b => CDBC, y => CDBC_C);
  nor_12: nor_gate port map (a => ABD, b => CDBC_C, y => y_pos);

end architecture;

q4/structural/sop_pos_function_tb.vhd
library ieee;
use ieee.std_logic_1164.all;
use ieee.numeric_std.all;

entity sop_pos_function_tb is
end entity;

architecture sim of sop_pos_function_tb is
  signal x1, x2, x3, x4 : std_logic := '0';
  signal y_sop, y_pos : std_logic;
  signal test_vector : std_logic_vector(3 downto 0);

begin
  UUT: entity work.sop_pos_function(structural_nor)
    port map(
      x1 => x1, x2 => x2, x3 => x3, x4 => x4,
      y_sop => y_sop, y_pos => y_pos
    );

    -- connect test vector to inputs
    x1 <= test_vector(3);
    x2 <= test_vector(2);
    x3 <= test_vector(1);
    x4 <= test_vector(0);

    -- test process
    process
    begin
      for i in 0 to 15 loop
        test_vector <= std_logic_vector(to_unsigned(i, 4));
        wait for 10 ns;
      end loop;

      report "Simulation complete";
      wait;
    end process;

end architecture;

q4/structural/waveform.vcd
$date
  Thu Feb 26 17:58:36 2026
$end
$version
  GHDL v0
$end
$timescale
  1 fs
$end
$scope module standard $end
$upscope $end
$scope module std_logic_1164 $end
$upscope $end
$scope module numeric_std $end
$upscope $end
$scope module sop_pos_function_tb $end
$var reg 1 ! x1 $end
$var reg 1 " x2 $end
$var reg 1 # x3 $end
$var reg 1 $ x4 $end
$var reg 1 % y_sop $end
$var reg 1 & y_pos $end
$var reg 4 ' test_vector[3:0] $end
$scope module uut $end
$var reg 1 ( x1 $end
$var reg 1 ) x2 $end
$var reg 1 * x3 $end
$var reg 1 + x4 $end
$var reg 1 , y_sop $end
$var reg 1 - y_pos $end
$var reg 1 . a_not $end
$var reg 1 / b_not $end
$var reg 1 0 c_not $end
$var reg 1 1 d_not $end
$var reg 1 2 ab $end
$var reg 1 3 ac_bc_cc $end
$var reg 1 4 abcomp $end
$var reg 1 5 abc $end
$var reg 1 6 y_sop_c $end
$var reg 1 7 c_dc $end
$var reg 1 8 b_c $end
$var reg 1 9 abd $end
$var reg 1 : cdbc $end
$var reg 1 ; cdbc_c $end
$scope module not_a $end
$var reg 1 < a $end
$var reg 1 = b $end
$var reg 1 > y $end
$upscope $end
$scope module not_b $end
$var reg 1 ? a $end
$var reg 1 @ b $end
$var reg 1 A y $end
$upscope $end
$scope module not_c $end
$var reg 1 B a $end
$var reg 1 C b $end
$var reg 1 D y $end
$upscope $end
$scope module not_d $end
$var reg 1 E a $end
$var reg 1 F b $end
$var reg 1 G y $end
$upscope $end
$scope module nor_1 $end
$var reg 1 H a $end
$var reg 1 I b $end
$var reg 1 J y $end
$upscope $end
$scope module nor_2 $end
$var reg 1 K a $end
$var reg 1 L b $end
$var reg 1 M y $end
$upscope $end
$scope module nor_3 $end
$var reg 1 N a $end
$var reg 1 O b $end
$var reg 1 P y $end
$upscope $end
$scope module nor_4 $end
$var reg 1 Q a $end
$var reg 1 R b $end
$var reg 1 S y $end
$upscope $end
$scope module nor_5 $end
$var reg 1 T a $end
$var reg 1 U b $end
$var reg 1 V y $end
$upscope $end
$scope module nor_6 $end
$var reg 1 W a $end
$var reg 1 X b $end
$var reg 1 Y y $end
$upscope $end
$scope module nor_7 $end
$var reg 1 Z a $end
$var reg 1 [ b $end
$var reg 1 \ y $end
$upscope $end
$scope module nor_8 $end
$var reg 1 ] a $end
$var reg 1 ^ b $end
$var reg 1 _ y $end
$upscope $end
$scope module nor_9 $end
$var reg 1 ` a $end
$var reg 1 a b $end
$var reg 1 b y $end
$upscope $end
$scope module nor_10 $end
$var reg 1 c a $end
$var reg 1 d b $end
$var reg 1 e y $end
$upscope $end
$scope module nor_11 $end
$var reg 1 f a $end
$var reg 1 g b $end
$var reg 1 h y $end
$upscope $end
$scope module nor_12 $end
$var reg 1 i a $end
$var reg 1 j b $end
$var reg 1 k y $end
$upscope $end
$upscope $end
$upscope $end
$enddefinitions $end
#0
0!
0"
0#
0$
0%
0&
b0000 '
0(
0)
0*
0+
0,
0-
1.
1/
10
11
02
03
14
05
16
07
18
09
0:
1;
0<
0=
1>
0?
0@
1A
0B
0C
1D
0E
0F
1G
1H
1I
0J
0K
1L
0M
0N
0O
1P
1Q
1R
0S
0T
0U
1V
1W
1X
0Y
0Z
1[
0\
0]
0^
1_
1`
1a
0b
0c
1d
0e
0f
0g
1h
0i
1j
0k
#10000000
1$
b0001 '
1+
01
17
1E
1F
0G
0[
1\
0a
1c
#20000000
1#
0$
1%
1&
b0010 '
1*
0+
1,
1-
00
11
13
06
07
08
1:
0;
1B
1C
0D
0E
0F
1G
0L
1M
0R
1T
0V
0W
0X
1Y
1Z
1[
0\
1^
0_
1a
0c
0d
1e
1f
1g
0h
0j
1k
#30000000
1$
b0011 '
1+
01
1E
1F
0G
0[
0a
#40000000
1"
0#
0$
0%
1&
b0100 '
1)
0*
0+
0,
1-
0/
10
11
03
16
07
1:
0;
1?
1@
0A
0B
0C
1D
0E
0F
1G
0I
1L
0M
1R
0T
1V
1W
1X
0Y
0Z
1[
0\
1]
0^
1a
0c
1e
1f
1g
0h
0j
1k
#50000000
1$
0&
b0101 '
1+
0-
01
17
0:
1;
1E
1F
0G
0[
1\
0a
1c
0e
0f
0g
1h
1j
0k
#60000000
1#
0$
1%
1&
b0110 '
1*
0+
1,
1-
00
11
13
06
07
1:
0;
1B
1C
0D
0E
0F
1G
0L
1M
0R
1T
0V
0W
0X
1Y
1Z
1[
0\
1^
1a
0c
1e
1f
1g
0h
0j
1k
#70000000
1$
b0111 '
1+
01
1E
1F
0G
0[
0a
#80000000
1!
0"
0#
0$
0%
0&
b1000 '
1(
0)
0*
0+
0,
0-
0.
1/
10
11
03
16
07
18
0:
1;
1<
1=
0>
0?
0@
1A
0B
0C
1D
0E
0F
1G
0H
1I
1L
0M
1R
0T
1V
1W
1X
0Y
0Z
1[
0\
0]
0^
1_
1a
0c
1d
0e
0f
0g
1h
1j
0k
#90000000
1$
b1001 '
1+
01
17
1E
1F
0G
0[
1\
0a
1c
#100000000
1#
0$
1%
1&
b1010 '
1*
0+
1,
1-
00
11
13
06
07
08
1:
0;
1B
1C
0D
0E
0F
1G
0L
1M
0R
1T
0V
0W
0X
1Y
1Z
1[
0\
1^
0_
1a
0c
0d
1e
1f
1g
0h
0j
1k
#110000000
1$
b1011 '
1+
01
1E
1F
0G
0[
0a
#120000000
1"
0#
0$
0%
1&
b1100 '
1)
0*
0+
0,
1-
0/
10
11
12
03
04
16
07
1:
0;
1?
1@
0A
0B
0C
1D
0E
0F
1G
0I
1J
1K
1L
0M
1N
1O
0P
0Q
1R
0T
1V
1W
1X
0Y
0Z
1[
0\
1]
0^
0`
1a
0c
1e
1f
1g
0h
0j
1k
#130000000
1$
0&
b1101 '
1+
0-
01
17
19
0:
1;
1E
1F
0G
0[
1\
0a
1b
1c
0e
0f
0g
1h
1i
1j
0k
#140000000
1#
0$
1%
1&
b1110 '
1*
0+
1,
1-
00
11
15
06
07
09
1:
0;
1B
1C
0D
0E
0F
1G
0L
0R
1S
1U
0V
0W
0X
1Y
1Z
1[
0\
1^
1a
0b
0c
1e
1f
1g
0h
0i
0j
1k
#150000000
1$
0&
b1111 '
1+
0-
01
19
1E
1F
0G
0[
0a
1b
1i
0k
