q4/behavioral/sop_pos_function.vhd
library ieee;
use ieee.std_logic_1164.all;
use ieee.numeric_std.all;

entity sop_pos_function is
  port (
    x1, x2, x3, x4 : in std_logic;
    y_sop, y_pos : out std_logic
  );
end entity;

architecture behavioral of sop_pos_function is
begin
  process(x1, x2, x3, x4)
    variable inputs : std_logic_vector(3 downto 0);
    variable input_int : integer;
  begin
    inputs := x1 & x2 & x3 & x4;
    input_int := to_integer(unsigned(inputs));

    case input_int is
      when 0 | 1 | 4 | 8 | 9 | 14 | 15 =>
        y_sop <= '1';
      when others =>
        y_sop <= '0';
    end case;


    case input_int is
      when 0 | 1 | 5 | 8 | 9 | 13 | 15 =>
        y_pos <= '0';
      when others =>
        y_pos <= '1';
    end case;
  end process;
end architecture;

q4/behavioral/sop_pos_function_tb.vhd
library ieee;
use ieee.std_logic_1164.all;
use ieee.numeric_std.all;

entity sop_pos_function_tb is
end entity;

architecture sim of sop_pos_function_tb is
  signal x1, x2, x3, x4 : std_logic := '0';
  signal y_sop, y_pos : std_logic;
  signal test_vector : std_logic_vector(3 downto 0);

begin
  UUT: entity work.sop_pos_function(behavioral)
    port map(
      x1 => x1, x2 => x2, x3 => x3, x4 => x4,
      y_sop => y_sop, y_pos => y_pos
    );

    -- connect test vector to inputs
    x1 <= test_vector(3);
    x2 <= test_vector(2);
    x3 <= test_vector(1);
    x4 <= test_vector(0);

    -- test process
    process
    begin
      for i in 0 to 15 loop
        test_vector <= std_logic_vector(to_unsigned(i, 4));
        wait for 10 ns;
      end loop;

      report "Simulation complete";
      wait;
    end process;

end architecture;

q4/behavioral/waveform.vcd
$date
  Thu Feb 26 12:29:36 2026
$end
$version
  GHDL v0
$end
$timescale
  1 fs
$end
$scope module standard $end
$upscope $end
$scope module std_logic_1164 $end
$upscope $end
$scope module numeric_std $end
$upscope $end
$scope module sop_pos_function_tb $end
$var reg 1 ! x1 $end
$var reg 1 " x2 $end
$var reg 1 # x3 $end
$var reg 1 $ x4 $end
$var reg 1 % y_sop $end
$var reg 1 & y_pos $end
$var reg 4 ' test_vector[3:0] $end
$scope module uut $end
$var reg 1 ( x1 $end
$var reg 1 ) x2 $end
$var reg 1 * x3 $end
$var reg 1 + x4 $end
$var reg 1 , y_sop $end
$var reg 1 - y_pos $end
$upscope $end
$upscope $end
$enddefinitions $end
#0
0!
0"
0#
0$
1%
0&
b0000 '
0(
0)
0*
0+
1,
0-
#10000000
1$
b0001 '
1+
#20000000
1#
0$
0%
1&
b0010 '
1*
0+
0,
1-
#30000000
1$
b0011 '
1+
#40000000
1"
0#
0$
1%
b0100 '
1)
0*
0+
1,
#50000000
1$
0%
0&
b0101 '
1+
0,
0-
#60000000
1#
0$
1&
b0110 '
1*
0+
1-
#70000000
1$
b0111 '
1+
#80000000
1!
0"
0#
0$
1%
0&
b1000 '
1(
0)
0*
0+
1,
0-
#90000000
1$
b1001 '
1+
#100000000
1#
0$
0%
1&
b1010 '
1*
0+
0,
1-
#110000000
1$
b1011 '
1+
#120000000
1"
0#
0$
b1100 '
1)
0*
0+
#130000000
1$
0&
b1101 '
1+
0-
#140000000
1#
0$
1%
1&
b1110 '
1*
0+
1,
1-
#150000000
1$
0&
b1111 '
1+
0-
