q6/mux2to1.vhd
library ieee;
use ieee.std_logic_1164.ALL;

entity mux2to1 is
    port (
        a   : in  std_logic;  -- input 0
        b   : in  std_logic;  -- input 1
        sel : in  std_logic;  -- select line
        y   : out std_logic   -- output
    );
end entity mux2to1;

architecture Behavioral of mux2to1 is
begin
    process(a, b, sel)
    begin
        if sel = '0' then
            y <= a;
        else
            y <= b;
        end if;
    end process;
end architecture Behavioral;

q6/mux4to1.vhd
library ieee;
use ieee.std_logic_1164.all;

entity mux4to1 is
  port (
    x1, x2, x3, x4 : in std_logic;
    s0, s1 : in std_logic;
    y : out std_logic
  );
end entity mux4to1;

architecture structural of mux4to1 is
  component mux2to1 is
    port (
      a, b, sel : in std_logic;
      y : out std_logic
    );
  end component;

  signal mux1_out : std_logic;
  signal mux2_out : std_logic;

begin
  mux1 : mux2to1 port map (
    a => x1,
    b => x2,
    sel => s0,
    y => mux1_out
  );

  mux2 : mux2to1 port map (
    a => x3,
    b => x4,
    sel => s0,
    y => mux2_out
  );

  mux3 : mux2to1 port map (
    a => mux1_out,
    b => mux2_out,
    sel => s1,
    y => y
  );

end architecture structural;

q6/mux4to1_tb.vhd
library ieee;
use ieee.std_logic_1164.all;
use ieee.numeric_std.all;

entity mux4to1_tb is
end entity mux4to1_tb;

architecture behavioral of mux4to1_tb is
  component mux4to1 is
    port (
      x1, x2, x3, x4, s0, s1 : in std_logic;
      y : out std_logic
    );
  end component;

  signal x1_tb : std_logic := '0';
  signal x2_tb : std_logic := '0';
  signal x3_tb : std_logic := '0';
  signal x4_tb : std_logic := '0';
  signal s0_tb : std_logic := '0';
  signal s1_tb : std_logic := '0';
  signal y_tb  : std_logic;

begin
  uut: mux4to1 port map(
    x1 => x1_tb,
    x2 => x2_tb,
    x3 => x3_tb,
    x4 => x4_tb,
    s0 => s0_tb,
    s1 => s1_tb,
    y => y_tb
  );

process
begin
  -- Pattern 1: x1=1, x2=0, x3=1, x4=0
    x1_tb <= '1';
    x2_tb <= '0';
    x3_tb <= '1';
    x4_tb <= '0';
    
    -- Test all select combinations
    -- s1s0 = 00 (select x1)
    s1_tb <= '0'; s0_tb <= '0';
    wait for 10 ns;
    
    -- s1s0 = 01 (select x2)
    s1_tb <= '0'; s0_tb <= '1';
    wait for 10 ns;
    
    -- s1s0 = 10 (select x3)
    s1_tb <= '1'; s0_tb <= '0';
    wait for 10 ns;
    
    -- s1s0 = 11 (select x4)
    s1_tb <= '1'; s0_tb <= '1';
    wait for 10 ns;
    
    -- Pattern 2: x1=0, x2=1, x3=0, x4=1
    x1_tb <= '0';
    x2_tb <= '1';
    x3_tb <= '0';
    x4_tb <= '1';
    
    -- Test all select combinations
    -- s1s0 = 00 (select x1)
    s1_tb <= '0'; s0_tb <= '0';
    wait for 10 ns;
    
    -- s1s0 = 01 (select x2)
    s1_tb <= '0'; s0_tb <= '1';
    wait for 10 ns;
    
    -- s1s0 = 10 (select x3)
    s1_tb <= '1'; s0_tb <= '0';
    wait for 10 ns;
    
    -- s1s0 = 11 (select x4)
    s1_tb <= '1'; s0_tb <= '1';
    wait for 10 ns;

    -- Pattern 3: x1=1, x2=0, x3=0, x4=1
    x1_tb <= '1';
    x2_tb <= '0';
    x3_tb <= '0';
    x4_tb <= '1';
    
    -- Test all select combinations
    -- s1s0 = 00 (select x1)
    s1_tb <= '0'; s0_tb <= '0';
    wait for 10 ns;
    
    -- s1s0 = 01 (select x2)
    s1_tb <= '0'; s0_tb <= '1';
    wait for 10 ns;
    
    -- s1s0 = 10 (select x3)
    s1_tb <= '1'; s0_tb <= '0';
    wait for 10 ns;
    
    -- s1s0 = 11 (select x4)
    s1_tb <= '1'; s0_tb <= '1';
    wait for 10 ns;
    
    report "Simulation completed successfully!";
    wait;
end process;

end architecture Behavioral;

q6/waveform.vcd
$date
  Thu Feb 26 18:57:28 2026
$end
$version
  GHDL v0
$end
$timescale
  1 fs
$end
$scope module standard $end
$upscope $end
$scope module std_logic_1164 $end
$upscope $end
$scope module numeric_std $end
$upscope $end
$scope module mux4to1_tb $end
$var reg 1 ! x1_tb $end
$var reg 1 " x2_tb $end
$var reg 1 # x3_tb $end
$var reg 1 $ x4_tb $end
$var reg 1 % s0_tb $end
$var reg 1 & s1_tb $end
$var reg 1 ' y_tb $end
$scope module uut $end
$var reg 1 ( x1 $end
$var reg 1 ) x2 $end
$var reg 1 * x3 $end
$var reg 1 + x4 $end
$var reg 1 , s0 $end
$var reg 1 - s1 $end
$var reg 1 . y $end
$var reg 1 / mux1_out $end
$var reg 1 0 mux2_out $end
$scope module mux1 $end
$var reg 1 1 a $end
$var reg 1 2 b $end
$var reg 1 3 sel $end
$var reg 1 4 y $end
$upscope $end
$scope module mux2 $end
$var reg 1 5 a $end
$var reg 1 6 b $end
$var reg 1 7 sel $end
$var reg 1 8 y $end
$upscope $end
$scope module mux3 $end
$var reg 1 9 a $end
$var reg 1 : b $end
$var reg 1 ; sel $end
$var reg 1 < y $end
$upscope $end
$upscope $end
$upscope $end
$enddefinitions $end
#0
1!
0"
1#
0$
0%
0&
1'
1(
0)
1*
0+
0,
0-
1.
1/
10
11
02
03
14
15
06
07
18
19
1:
0;
1<
#10000000
1%
0'
1,
0.
0/
00
13
04
17
08
09
0:
0<
#20000000
0%
1&
1'
0,
1-
1.
1/
10
03
14
07
18
19
1:
1;
1<
#30000000
1%
0'
1,
0.
0/
00
13
04
17
08
09
0:
0<
#40000000
0!
1"
0#
1$
0%
0&
0(
1)
0*
1+
0,
0-
01
12
03
05
16
07
0;
#50000000
1%
1'
1,
1.
1/
10
13
14
17
18
19
1:
1<
#60000000
0%
1&
0'
0,
1-
0.
0/
00
03
04
07
08
09
0:
1;
0<
#70000000
1%
1'
1,
1.
1/
10
13
14
17
18
19
1:
1<
#80000000
1!
0"
0%
0&
1(
0)
0,
0-
00
11
02
03
07
08
0:
0;
#90000000
1%
0'
1,
0.
0/
10
13
04
17
18
09
1:
0<
#100000000
0%
1&
0'
0,
1-
0.
1/
00
03
14
07
08
19
0:
1;
0<
#110000000
1%
1'
1,
1.
0/
10
13
04
17
18
09
1:
1<
