q2/behavioral/bcd_to_gray.vhd
library ieee;
use ieee.std_logic_1164.all;
use ieee.numeric_std.all;

entity bcd_to_gray is
  port (
    a, b, c, d : in  std_logic;
    w, x, y, z : out std_logic
  );
end entity;

architecture behavioral of bcd_to_gray is
begin
  process(a, b, c, d)
    variable bcd_val : integer;
  begin
    bcd_val := to_integer(unsigned'(a & b & c & d));
    
    -- default outputs (don't cares for invalid BCD)
    w <= '-';
    x <= '-';
    y <= '-';
    z <= '-';
    
    -- only process 0-9 BCD inputs
    if bcd_val <= 9 then
      w <= a;
      x <= a xor b;
      y <= b xor c;
      z <= c xor d;
    end if;
  end process;
end architecture;

q2/behavioral/bcd_to_gray_tb.vhd
library ieee;
use ieee.std_logic_1164.all;
use ieee.numeric_std.all;

entity bcd_to_gray_tb is
end entity;

architecture sim of bcd_to_gray_tb is
  signal a, b, c, d : std_logic := '0';
  signal w, x, y, z : std_logic;
  signal test_vector : std_logic_vector(3 downto 0);

begin
  -- uut for dataflow
  UUT: entity work.bcd_to_gray(behavioral)
    port map(
      a => a, b => b, c => c, d => d,
      w => w, x => x, y => y, z => z
    );

  a <= test_vector(3);
  b <= test_vector(2);
  c <= test_vector(1);
  d <= test_vector(0);

  process
  begin
    for i in 0 to 15 loop
      test_vector <= std_logic_vector(to_unsigned(i, 4));
      wait for 10 ns;
      -- Optional: print values to console
      report "Input: " & integer'image(i) & 
             " (" & std_logic'image(a) & std_logic'image(b) & 
                    std_logic'image(c) & std_logic'image(d) & ")" &
             " Output: " & std_logic'image(w) & std_logic'image(x) & 
                           std_logic'image(y) & std_logic'image(z);
    end loop;
    report "Simulation complete";
    wait;
  end process;
end architecture;

q2/behavioral/waveform.vcd
$date
  Thu Feb 26 08:37:01 2026
$end
$version
  GHDL v0
$end
$timescale
  1 fs
$end
$scope module standard $end
$upscope $end
$scope module std_logic_1164 $end
$upscope $end
$scope module numeric_std $end
$upscope $end
$scope module bcd_to_gray_tb $end
$var reg 1 ! a $end
$var reg 1 " b $end
$var reg 1 # c $end
$var reg 1 $ d $end
$var reg 1 % w $end
$var reg 1 & x $end
$var reg 1 ' y $end
$var reg 1 ( z $end
$var reg 4 ) test_vector[3:0] $end
$scope module uut $end
$var reg 1 * a $end
$var reg 1 + b $end
$var reg 1 , c $end
$var reg 1 - d $end
$var reg 1 . w $end
$var reg 1 / x $end
$var reg 1 0 y $end
$var reg 1 1 z $end
$upscope $end
$upscope $end
$enddefinitions $end
#0
0!
0"
0#
0$
0%
0&
0'
0(
b0000 )
0*
0+
0,
0-
0.
0/
00
01
#10000000
1$
1(
b0001 )
1-
0.
0/
00
11
#20000000
1#
0$
1'
b0010 )
1,
0-
0.
0/
10
11
#30000000
1$
0(
b0011 )
1-
0.
0/
10
01
#40000000
1"
0#
0$
1&
b0100 )
1+
0,
0-
0.
1/
10
01
#50000000
1$
1(
b0101 )
1-
0.
1/
10
11
#60000000
1#
0$
0'
b0110 )
1,
0-
0.
1/
00
11
#70000000
1$
0(
b0111 )
1-
0.
1/
00
01
#80000000
1!
0"
0#
0$
1%
b1000 )
1*
0+
0,
0-
1.
1/
00
01
#90000000
1$
1(
b1001 )
1-
1.
1/
00
11
#100000000
1#
0$
-%
-&
-'
-(
b1010 )
1,
0-
-.
-/
-0
-1
#110000000
1$
b1011 )
1-
#120000000
1"
0#
0$
b1100 )
1+
0,
0-
#130000000
1$
b1101 )
1-
#140000000
1#
0$
b1110 )
1,
0-
#150000000
1$
b1111 )
1-
