q1/behavioral/q1.vhd
library ieee;
use ieee.std_logic_1164.all;

entity logic_circuit is
  port (
    x1, x2, x3, x4  : in std_logic;
    f               : out std_logic
       );
end entity;

architecture behavioral of logic_circuit is
begin
  -- process is sensitive to all inputs
  process(x1, x2, x3, x4)
    variable A_B, BC, BC_C, A_C, BC_D : std_logic;
  begin
    -- calculate intermediate terms
    A_B := x1 and x2;
    BC := not x2;
    BC_C := BC and x3;
    A_C := A_B or BC_C;
    BC_D := BC_C and x4;

    -- assign final output
    f <= A_C or BC_D; -- f = A_D
  end process;
end architecture;

q1/behavioral/q1_tb.vhd
library ieee;
use ieee.std_logic_1164.all;
use ieee.numeric_std.all;

entity q1_tb is
end entity;

architecture sim of q1_tb is
  signal x1, x2, x3, x4 : std_logic := '0';
  signal f : std_logic;
begin
  -- unit under test - using behavioral architecture
  UUT: entity work.logic_circuit(behavioral)
    port map(x1 => x1, x2 => x2, x3 => x3, x4 => x4, f => f);

  process
    variable input_vec : unsigned(3 downto 0);
  begin
    -- iterate through all 16 combinations
    for i in 0 to 15 loop
      input_vec := to_unsigned(i, 4);
      x4 <= input_vec(3);
      x3 <= input_vec(2);
      x2 <= input_vec(1);
      x1 <= input_vec(0);
      wait for 10 ns;
    end loop;
    
    -- stop simulation
    wait;
  end process;
end architecture;

q1/behavioral/waveform.vcd
$date
  Wed Feb 25 23:20:58 2026
$end
$version
  GHDL v0
$end
$timescale
  1 fs
$end
$scope module standard $end
$upscope $end
$scope module std_logic_1164 $end
$upscope $end
$scope module numeric_std $end
$upscope $end
$scope module q1_tb $end
$var reg 1 ! x1 $end
$var reg 1 " x2 $end
$var reg 1 # x3 $end
$var reg 1 $ x4 $end
$var reg 1 % f $end
$scope module uut $end
$var reg 1 & x1 $end
$var reg 1 ' x2 $end
$var reg 1 ( x3 $end
$var reg 1 ) x4 $end
$var reg 1 * f $end
$upscope $end
$upscope $end
$enddefinitions $end
#0
0!
0"
0#
0$
0%
0&
0'
0(
0)
0*
#10000000
1!
1&
#20000000
0!
1"
0&
1'
#30000000
1!
1%
1&
1*
#40000000
0!
0"
1#
0&
0'
1(
#50000000
1!
1&
#60000000
0!
1"
0%
0&
1'
0*
#70000000
1!
1%
1&
1*
#80000000
0!
0"
0#
1$
0%
0&
0'
0(
1)
0*
#90000000
1!
1&
#100000000
0!
1"
0&
1'
#110000000
1!
1%
1&
1*
#120000000
0!
0"
1#
0&
0'
1(
#130000000
1!
1&
#140000000
0!
1"
0%
0&
1'
0*
#150000000
1!
1%
1&
1*
